AUTHORS.rst
LICENSE.txt
MANIFEST.in
README.md
setup.cfg
setup.py
src/pyforest/__init__.py
src/pyforest/__main__.py
src/pyforest/_importable.py
src/pyforest/_imports.py
src/pyforest/auto_import.py
src/pyforest/package-lock.json
src/pyforest/package.json
src/pyforest/user_specific_imports.py
src/pyforest/utils.py
src/pyforest.egg-info/PKG-INFO
src/pyforest.egg-info/SOURCES.txt
src/pyforest.egg-info/dependency_links.txt
src/pyforest.egg-info/not-zip-safe
src/pyforest.egg-info/requires.txt
src/pyforest.egg-info/top_level.txt
src/pyforest/static/labextension.js
src/pyforest/static/nbextension.js
src/pyforest/static/utils.js
tests/test_pyforest.py