Metadata-Version: 2.1
Name: pyforest
Version: 1.1.1
Summary: Lazy-import of all popular Python Data Science libraries. Stop writing the same imports over and over again.
Home-page: https://github.com/8080labs/pyforest/
Author: Florian Wetschoreck, Guido Drechsel, Tobias Krabel
Author-email: info@8080labs.com
License: mit
Project-URL: Documentation, https://github.com/8080labs/pyforest/
Platform: any
Classifier: Development Status :: 4 - Beta
Classifier: Programming Language :: Python
Requires-Python: >=3.6
License-File: LICENSE.txt
License-File: AUTHORS.rst
Provides-Extra: testing
Requires-Dist: pytest; extra == "testing"
Requires-Dist: pytest-cov; extra == "testing"
